setup.py
culinary/__init__.py
culinary/command.py
culinary/core.py
culinary/decorator.py
culinary/dir.py
culinary/file.py
culinary/group.py
culinary/misc.py
culinary/mode.py
culinary/option.py
culinary/package.py
culinary/postgresql.py
culinary/process.py
culinary/python.py
culinary/repository.py
culinary/ssh.py
culinary/text.py
culinary/user.py
culinary.egg-info/PKG-INFO
culinary.egg-info/SOURCES.txt
culinary.egg-info/dependency_links.txt
culinary.egg-info/requires.txt
culinary.egg-info/top_level.txt