Metadata-Version: 1.1
Name: culinary
Version: 0.1.0
Summary: A fork of Cuisine for those who like namespaces.
Home-page: http://github.com/kolanos/culinary
Author: Michael Lavers
Author-email: kolanos@gmail.com
License: UNKNOWN
Download-URL: https://github.com/kolanos/culinary/tarball/0.1.0
Keywords: fabric,chef,ssh,cuisine
Platform: UNKNOWN
Classifier: Programming Language :: Python
Classifier: Development Status :: 3 - Alpha
Classifier: Natural Language :: English
Classifier: Environment :: Web Environment
Classifier: Intended Audience :: Developers
Classifier: Operating System :: OS Independent
Classifier: Topic :: Utilities
